README.rst
setup.py
bin/clarify_brightcove_sync
clarify_brightcove_sync/__init__.py
clarify_brightcove_sync/brightcove_api_client.py
clarify_brightcove_sync/clarify_brightcove_bridge.py
clarify_brightcove_sync.egg-info/PKG-INFO
clarify_brightcove_sync.egg-info/SOURCES.txt
clarify_brightcove_sync.egg-info/dependency_links.txt
clarify_brightcove_sync.egg-info/not-zip-safe
clarify_brightcove_sync.egg-info/requires.txt
clarify_brightcove_sync.egg-info/top_level.txt