Metadata-Version: 1.1
Name: clarify-brightcove-sync
Version: 0.0.1
Summary: Commandline tool to sync a Brightcove video library to Clarify.
Home-page: https://github.com/Clarify/clarify_brightcove_sync
Author: Ivo Rothschild
Author-email: ivo@clarify.io
License: MIT
Keywords: clarify_brightcove_sync clarify brightcove video audio search
Platform: UNKNOWN
Classifier: Development Status :: 5 - Production/Stable
Classifier: Intended Audience :: Developers
Classifier: License :: OSI Approved :: MIT License
Classifier: Natural Language :: English
Classifier: Programming Language :: Python :: 3
